eventum_plugins/__init__.py
eventum_plugins/event/__init__.py
eventum_plugins/event/base.py
eventum_plugins/event/jinja.py
eventum_plugins/event/jinja_modules/__init__.py
eventum_plugins/event/jinja_modules/py.py
eventum_plugins/event/jinja_modules/rand.py
eventum_plugins/event/tests/static/sample.csv
eventum_plugins/event/tests/test_jinja.py
eventum_plugins/input/__init__.py
eventum_plugins/input/base.py
eventum_plugins/input/cron.py
eventum_plugins/input/linspace.py
eventum_plugins/input/sample.py
eventum_plugins/input/tests/static/time_pattern_invalid.yml
eventum_plugins/input/tests/static/time_pattern_valid.yml
eventum_plugins/input/tests/test_cron.py
eventum_plugins/input/tests/test_linspace.py
eventum_plugins/input/tests/test_sample.py
eventum_plugins/input/tests/test_time_patterns.py
eventum_plugins/input/tests/test_timer.py
eventum_plugins/input/tests/test_timestamps.py
eventum_plugins/input/time_patterns.py
eventum_plugins/input/timer.py
eventum_plugins/input/timestamps.py
eventum_plugins/output/__init__.py
eventum_plugins/output/base.py
eventum_plugins/output/file.py
eventum_plugins/output/opensearch.py
eventum_plugins/output/stdout.py
eventum_plugins/output/tests/test_file.py
eventum_plugins/output/tests/test_opensearch.py
eventum_plugins/py.typed
eventum_plugins/utils/__init__.py
eventum_plugins/utils/modules.py
eventum_plugins/utils/numpy_time.py
eventum_plugins/utils/relative_time.py
eventum_plugins/utils/tests/test_relative_time.py
eventum_plugins/utils/tests/test_timeseries.py
eventum_plugins/utils/timeseries.py
eventum_plugins-1.1.1.dist-info/LICENSE
eventum_plugins-1.1.1.dist-info/METADATA
eventum_plugins-1.1.1.dist-info/WHEEL
eventum_plugins-1.1.1.dist-info/RECORD
